localstack_extension_tailscale/__init__.py
localstack_extension_tailscale/container.py
localstack_extension_tailscale/extension.py
localstack_extension_tailscale-0.1.0.dist-info/METADATA
localstack_extension_tailscale-0.1.0.dist-info/WHEEL
localstack_extension_tailscale-0.1.0.dist-info/entry_points.txt
localstack_extension_tailscale-0.1.0.dist-info/top_level.txt
localstack_extension_tailscale-0.1.0.dist-info/RECORD
